{
    "version": "0.23.2",
    "architecture": {
        "64bit": {
            "url": "https://github.com/raystack/frontier/releases/download/v0.23.2/frontier_Windows_x86_64.zip",
            "bin": [
                "frontier.exe"
            ],
            "hash": "3fefa5724f25a569282a1b606a68463b90e7294fd6a54906b995fa89d41b16cc"
        },
        "arm64": {
            "url": "https://github.com/raystack/frontier/releases/download/v0.23.2/frontier_Windows_arm64.zip",
            "bin": [
                "frontier.exe"
            ],
            "hash": "db03e15e77cdcde6b1eb873a6c339e31a7c6a3b9e2eed9ef2527ae433820d6d0"
        }
    },
    "homepage": "https://github.com/raystack/frontier",
    "license": "Apache 2.0",
    "description": "Identity and authorization system"
}