{
    "version": "0.75.1",
    "architecture": {
        "64bit": {
            "url": "https://github.com/raystack/frontier/releases/download/v0.75.1/frontier_Windows_x86_64.zip",
            "bin": [
                "frontier.exe"
            ],
            "hash": "dcc0c97203cf3804115c585c8de0f63ff278271e60dde7108ba9920a537dca7f"
        },
        "arm64": {
            "url": "https://github.com/raystack/frontier/releases/download/v0.75.1/frontier_Windows_arm64.zip",
            "bin": [
                "frontier.exe"
            ],
            "hash": "2b21c9d3b991e50d48e7c4e45d1446031d29e76ebde4d23114b23b9a9405b335"
        }
    },
    "homepage": "https://github.com/raystack/frontier",
    "license": "Apache 2.0",
    "description": "Identity and authorization system"
}